py_ogp_parser/__init__.py
py_ogp_parser/parser.py
py_ogp_parser-0.2.1.dist-info/METADATA
py_ogp_parser-0.2.1.dist-info/RECORD
py_ogp_parser-0.2.1.dist-info/WHEEL
py_ogp_parser-0.2.1.dist-info/top_level.txt
