Metadata-Version: 1.1
Name: py-ogp-parser
Version: 0.2.1
Summary: Opengraph Protocol Parser
Home-page: https://github.com/ukyoda/py-ogp-parser
Author: ukyoda
Author-email: black12172001@hotmail.co.jp
License: MIT
Keywords: opengraph beautifulsoup4 requests scraping
Platform: UNKNOWN
Classifier: Programming Language :: Python :: 3.6
